restack_integrations_gemini/__init__.py
restack_integrations_gemini/functions/__init__.py
restack_integrations_gemini/functions/generate_content.py
restack_integrations_gemini/py.typed
restack_integrations_gemini/service.py
restack_integrations_gemini/task_queue.py
restack_integrations_gemini/utils/__init__.py
restack_integrations_gemini-0.0.6.dist-info/METADATA
restack_integrations_gemini-0.0.6.dist-info/WHEEL
restack_integrations_gemini-0.0.6.dist-info/RECORD
