Metadata-Version: 2.1
Name: restack_integrations_gemini
Version: 0.0.6
Summary: Gemini integration for Restack AI
Author: Restack Team
Author-email: service@restack.io
Requires-Python: >=3.9,<4.0
Classifier: Programming Language :: Python :: 3
Classifier: Programming Language :: Python :: 3.9
Classifier: Programming Language :: Python :: 3.10
Classifier: Programming Language :: Python :: 3.11
Classifier: Programming Language :: Python :: 3.12
Requires-Dist: google-generativeai (>=0.8.3,<0.9.0)
Requires-Dist: pydantic (>=2.9.2,<3.0.0)
Requires-Dist: restack_ai (>=0.0.11,<0.0.12)
